CHANGES.txt
README.txt
TODO.txt
bootstrap.py
buildout.cfg
setup.py
zopeproject/__init__.py
zopeproject/main.py
zopeproject/script.py
zopeproject/templates.py
zopeproject.egg-info/PKG-INFO
zopeproject.egg-info/SOURCES.txt
zopeproject.egg-info/dependency_links.txt
zopeproject.egg-info/entry_points.txt
zopeproject.egg-info/not-zip-safe
zopeproject.egg-info/requires.txt
zopeproject.egg-info/top_level.txt
zopeproject/zope_app/setup.py_tmpl
zopeproject/zope_app/src/+package+/__init__.py
zopeproject/zope_app/src/+package+/configure.zcml_tmpl
zopeproject/zope_app/src/+package+/ftesting.zcml_tmpl
zopeproject/zope_app/src/+package+/startup.py
zopeproject/zope_app/src/+package+/testing.py
zopeproject/zope_deploy/apidoc.zcml
zopeproject/zope_deploy/buildout.cfg_tmpl
zopeproject/zope_deploy/debug.ini_tmpl
zopeproject/zope_deploy/deploy.ini_tmpl
zopeproject/zope_deploy/site.zcml_tmpl
zopeproject/zope_deploy/zdaemon.conf
zopeproject/zope_deploy/zope.conf
zopeproject/zope_deploy/log/README.txt
zopeproject/zope_deploy/var/README.txt