Metadata-Version: 1.0
Name: zopeproject
Version: 0.4.2
Summary: Tools and scripts for creating development sandboxes for web applications that primarily use Zope
Home-page: http://cheeseshop.python.org/pypi/zopeproject
Author: Philipp von Weitershausen
Author-email: philipp@weitershausen.de
License: ZPL
Download-URL: svn://svn.zope.org/repos/main/Sandbox/philikon/zopeproject/trunk#egg=zopeproject-dev
Platform: UNKNOWN
Classifier: Environment :: Console
Classifier: Intended Audience :: Developers
Classifier: License :: OSI Approved :: Zope Public License
Classifier: Programming Language :: Python
Classifier: Topic :: Internet :: WWW/HTTP :: WSGI
Classifier: Framework :: Zope3
